README.rst
setup.py
meteorology/__init__.py
meteorology/constants.py
meteorology/humidity.py
meteorology/radiation.py
meteorology/temperature.py
meteorology/wind.py
meteorology.egg-info/PKG-INFO
meteorology.egg-info/SOURCES.txt
meteorology.egg-info/dependency_links.txt
meteorology.egg-info/requires.txt
meteorology.egg-info/top_level.txt