Metadata-Version: 1.1
Name: meteorology
Version: 0.0.10
Summary: utilities for meteorological calculations
Home-page: https://gitlab.com/nobodyinperson/python3-meteorology
Author: Yann Büchau
Author-email: yann.buechau@web.de
License: GPLv3
Keywords: meteorology
Platform: UNKNOWN
Classifier: License :: OSI Approved :: GNU General Public License v3 (GPLv3)
Classifier: Programming Language :: Python :: 3.5
Classifier: Operating System :: OS Independent
Classifier: Topic :: Scientific/Engineering :: Atmospheric Science
